README.md
setup.py
mop/__init__.py
mop/__main__.py
mop_rules.egg-info/PKG-INFO
mop_rules.egg-info/SOURCES.txt
mop_rules.egg-info/dependency_links.txt
mop_rules.egg-info/entry_points.txt
mop_rules.egg-info/requires.txt
mop_rules.egg-info/top_level.txt