Metadata-Version: 2.1
Name: mop-rules
Version: 0.0.1
Summary: Полезная утилита, призванная сделать ваш python проект чище
Home-page: https://github.com/ogurechik/mop-rules
Author: Oleg Silver
Author-email: rav-navini-gego-cutropal@yandex.ru
License: MIT
Platform: UNKNOWN
Classifier: Programming Language :: Python :: 3
Classifier: License :: OSI Approved :: MIT License
Classifier: Operating System :: OS Independent
Requires-Python: >=3.6
